myalias/__init__.py
myalias/cli.py
myalias/commands/__init__.py
myalias/commands/add_alias_command.py
myalias/commands/import_aliases_command.py
myalias/commands/list_alias_command.py
myalias/commands/remove_alias_command.py
myalias/core/__init__.py
myalias/core/commands/__init__.py
myalias/core/commands/about_command.py
myalias/core/commands/setup_command.py
myalias/core/interfaces/__init__.py
myalias/core/interfaces/command_interface.py
myalias/core/interfaces/service_interface.py
myalias/core/services/__init__.py
myalias/core/services/append_commands_cli_service.py
myalias/core/services/create_folders_app_service.py
myalias/core/services/get_all_command_service.py
myalias/core/services/get_path_application_service.py
myalias/core/services/get_path_config_service.py
myalias/core/services/get_version_app_service.py
myalias/core/services/transform_file_into_tuples_list_service.py
myalias/core/services/update_version_app_service.py
myalias-0.2.2.dist-info/LICENSE
myalias-0.2.2.dist-info/METADATA
myalias-0.2.2.dist-info/WHEEL
myalias-0.2.2.dist-info/entry_points.txt
myalias-0.2.2.dist-info/RECORD
